{
  "members": [
    {
      "avatar_url": "htttp://testeeeeee.com",
      "name": "terste",
      "email": "teste@teste.com",
      "birth": 71065468800000,
      "gender": "F",
      "blood": "A+",
      "weight": "44",
      "height": "23423",
      "id": 1
    },
    {
      "avatar_url": "https://ath2.unileverservices.com/wp-content/uploads/sites/2/2016/05/cortes-para-pouco-cabelo-em-homem-500x500.jpg",
      "name": "Luciano",
      "email": "luciano@teste.com",
      "birth": 255830400000,
      "gender": "M",
      "blood": "AB-",
      "weight": "97",
      "height": "186",
      "id": 2
    }
  ],
  "instructors": [
    {
      "id": 3,
      "avatar_url": "https://www.google.com/imgres?imgurl=https%3A%2F%2Fwww.lotus-qa.com%2Fwp-content%2Fuploads%2F2020%2F02%2Ftesting.jpg&imgrefurl=https%3A%2F%2Fwww.lotus-qa.com%2Ftesters-need-know-testing%2F&tbnid=d8BigfbA3M0-TM&vet=12ahUKEwiP-4bOj-nqAhUhFLkGHa6JADAQMygAegUIARCZAQ..i&docid=F2sneNwdX7yysM&w=1508&h=706&q=testing&client=opera-gx&ved=2ahUKEwiP-4bOj-nqAhUhFLkGHa6JADAQMygAegUIARCZAQ",
      "name": "Leonard",
      "birth": 972604800000,
      "gender": "M",
      "services": "taekwondo",
      "created_at": 1595876980847
    },
    {
      "id": 4,
      "avatar_url": "htttp://asdasd.com",
      "name": "Lucas",
      "birth": 940982400000,
      "gender": "M",
      "services": "natação, judô",
      "created_at": 1595963181081
    }
  ]
}